vvecon/__init__.py
vvecon/__main__.py
vvecon/__version__.py
vvecon/rest_api/App.py
vvecon/rest_api/__init__.py
vvecon/rest_api/__version__.py
vvecon/rest_api/connections/MySQLDBConnection.py
vvecon/rest_api/connections/MySQLDBSingleConnection.py
vvecon/rest_api/connections/__init__.py
vvecon/rest_api/socket/SockAbort.py
vvecon/rest_api/socket/SockParser.py
vvecon/rest_api/socket/Socket.py
vvecon/rest_api/socket/SocketIO.py
vvecon/rest_api/socket/__init__.py
vvecon/rest_api/test/__init__.py
vvecon/rest_api/test/sample/Resources.py
vvecon/rest_api/test/sample/__init__.py
vvecon/rest_api/test/sample/main.py
vvecon/rest_api/test/sample/Abort/Abort.py
vvecon/rest_api/test/sample/Abort/__init__.py
vvecon/rest_api/test/sample/Controller/UserController.py
vvecon/rest_api/test/sample/Controller/__init__.py
vvecon/rest_api/test/sample/DB/__init__.py
vvecon/rest_api/test/sample/DB/backup.py
vvecon/rest_api/test/sample/DB/merge.py
vvecon/rest_api/test/sample/DB/restart.py
vvecon/rest_api/test/sample/DB/upload web.py
vvecon/rest_api/test/sample/DB/upload.py
vvecon/rest_api/test/sample/Doc/SocketTester.py
vvecon/rest_api/test/sample/Doc/UnitTester.py
vvecon/rest_api/test/sample/Doc/__init__.py
vvecon/rest_api/test/sample/Doc/urls.py
vvecon/rest_api/test/sample/Model/UserModel.py
vvecon/rest_api/test/sample/Model/__init__.py
vvecon/rest_api/test/sample/Parsers/UserParser.py
vvecon/rest_api/test/sample/Parsers/__init__.py
vvecon/rest_api/test/sample/tmp/__init__.py
vvecon/rest_api/utils/Abort.py
vvecon/rest_api/utils/Controller.py
vvecon/rest_api/utils/Mail.py
vvecon/rest_api/utils/Model.py
vvecon/rest_api/utils/ReqParser.py
vvecon/rest_api/utils/Router.py
vvecon/rest_api/utils/Types.py
vvecon/rest_api/utils/__init__.py
vvecon-1.0.4.dist-info/LICENSE
vvecon-1.0.4.dist-info/METADATA
vvecon-1.0.4.dist-info/WHEEL
vvecon-1.0.4.dist-info/top_level.txt
vvecon-1.0.4.dist-info/RECORD
